labjack/__init__.py
labjack/ljm/__init__.py
labjack/ljm/constants.py
labjack/ljm/errorcodes.py
labjack/ljm/ljm.py
labjack_ljm-1.23.0.dist-info/LICENSE.TXT
labjack_ljm-1.23.0.dist-info/METADATA
labjack_ljm-1.23.0.dist-info/WHEEL
labjack_ljm-1.23.0.dist-info/top_level.txt
labjack_ljm-1.23.0.dist-info/RECORD
